pymt_roms/__init__.py
pymt_roms/bmi.py
pymt_roms/data/Roms/api.yaml
pymt_roms/data/Roms/config_file.yaml
pymt_roms/data/Roms/info.yaml
pymt_roms/data/Roms/parameters.yaml
pymt_roms/data/Roms/run.yaml
pymt_roms-0.1.dist-info/LICENSE
pymt_roms-0.1.dist-info/METADATA
pymt_roms-0.1.dist-info/WHEEL
pymt_roms-0.1.dist-info/entry_points.txt
pymt_roms-0.1.dist-info/top_level.txt
pymt_roms-0.1.dist-info/RECORD
